[
  { "pattern": "google-analytics.com", "category": "Analytics" },
  { "pattern": "analytics.google.com", "category": "Analytics" },
  { "pattern": "plausible.io", "category": "Analytics" },
  { "pattern": "usefathom.com", "category": "Analytics" },
  { "pattern": "amplitude.com", "category": "Analytics" },
  { "pattern": "mixpanel.com", "category": "Analytics" },
  { "pattern": "segment.io", "category": "Analytics" },
  { "pattern": "heap.io", "category": "Analytics" },
  { "pattern": "posthog.com", "category": "Analytics" },
  { "pattern": "doubleclick.net", "category": "Advertising" },
  { "pattern": "googleadservices.com", "category": "Advertising" },
  { "pattern": "googlesyndication.com", "category": "Advertising" },
  { "pattern": "adservice.google.com", "category": "Advertising" },
  { "pattern": "ads-twitter.com", "category": "Advertising" },
  { "pattern": "taboola.com", "category": "Advertising" },
  { "pattern": "outbrain.com", "category": "Advertising" },
  { "pattern": "quantserve.com", "category": "Advertising" },
  { "pattern": "scorecardresearch.com", "category": "Advertising" },
  { "pattern": "connect.facebook.net", "category": "Social" },
  { "pattern": "facebook.com", "category": "Social" },
  { "pattern": "tiktok.com", "category": "Social" },
  { "pattern": "snap.licdn.com", "category": "Social" },
  { "pattern": "linkedin.com", "category": "Social" },
  { "pattern": "platform.twitter.com", "category": "Social" },
  { "pattern": "x.com", "category": "Social" },
  { "pattern": "pinterest.com", "category": "Social" },
  { "pattern": "hotjar.com", "category": "Session replay" },
  { "pattern": "clarity.ms", "category": "Session replay" },
  { "pattern": "fullstory.com", "category": "Session replay" },
  { "pattern": "mouseflow.com", "category": "Session replay" },
  { "pattern": "luckyorange.com", "category": "Session replay" },
  { "pattern": "logrocket.com", "category": "Session replay" },
  { "pattern": "smartlook.com", "category": "Session replay" },
  { "pattern": "googletagmanager.com", "category": "Tag manager" },
  { "pattern": "tealiumiq.com", "category": "Tag manager" },
  { "pattern": "tagcommander.com", "category": "Tag manager" },
  { "pattern": "ensighten.com", "category": "Tag manager" },
  { "pattern": "cloudflare.com", "category": "CDN / functional" },
  { "pattern": "cdnjs.cloudflare.com", "category": "CDN / functional" },
  { "pattern": "jsdelivr.net", "category": "CDN / functional" },
  { "pattern": "unpkg.com", "category": "CDN / functional" },
  { "pattern": "bootstrapcdn.com", "category": "CDN / functional" },
  { "pattern": "fonts.googleapis.com", "category": "CDN / functional" },
  { "pattern": "fonts.gstatic.com", "category": "CDN / functional" },
  { "pattern": "gstatic.com", "category": "CDN / functional" }
]
